topsis_samiksha_102317096/__init__.py
topsis_samiksha_102317096/__main__.py
topsis_samiksha_102317096/topsis.py
topsis_samiksha_102317096-0.1.1.dist-info/licenses/LICENSE
topsis_samiksha_102317096-0.1.1.dist-info/METADATA
topsis_samiksha_102317096-0.1.1.dist-info/WHEEL
topsis_samiksha_102317096-0.1.1.dist-info/entry_points.txt
topsis_samiksha_102317096-0.1.1.dist-info/top_level.txt
topsis_samiksha_102317096-0.1.1.dist-info/RECORD
