Metadata-Version: 2.4
Name: Topsis-Samiksha-102317096
Version: 0.1.1
Summary: A Python package for TOPSIS analysis
Home-page: https://github.com/samiksha-bansal1/Topsis-Samiksha-102317096
Author: Samiksha
Author-email: Samiksha <samikshabansal2005@example.com>
License: MIT
Requires-Python: >=3.6
License-File: LICENSE
Requires-Dist: numpy
Requires-Dist: pandas
Dynamic: author
Dynamic: home-page
Dynamic: license-file
Dynamic: requires-python
